Metadata-Version: 2.1
Name: MeuPrimeiroPacoteLibpythonpro
Version: 0.2
Summary: Módulo para exemplificar a construção de projetos no curso Pytools
Home-page: https://github.com/Arthurregismais/libpythonpro
Author: Arthur Régis Mais
Author-email: arthur.regismais@hotmail.com
License:                     GNU AFFERO GENERAL PUBLIC LICENSE
Platform: UNKNOWN
Classifier: Development Status :: 2 - Pre-Alpha
Classifier: Environment :: Console
Classifier: Intended Audience :: Developers
Classifier: License :: OSI Approved :: GNU Affero General Public License v3 or later (AGPLv3+)
Classifier: Operating System :: OS Independent
Classifier: Programming Language :: Python
Classifier: Programming Language :: Python :: 3.9
Classifier: Framework :: Pytest
License-File: LICENSE
